setup.py
msh/__init__.py
msh/msh.py
msh.egg-info/PKG-INFO
msh.egg-info/SOURCES.txt
msh.egg-info/dependency_links.txt
msh.egg-info/requires.txt
msh.egg-info/top_level.txt
msh.egg-info/scripts/__init__.py
msh.egg-info/scripts/msh
msh/api/__init__.py
msh/api/api.py
msh/api/inputClient.py
msh/api/outputClient.py
msh/constants/Constants.py
msh/constants/ParamsException.py
msh/constants/PasswordErrorException.py
msh/constants/__init__.py
msh/i18n/__init__.py
msh/service/__init__.py
msh/service/color/__init__.py
msh/service/db/__init__.py
msh/service/db/dbService.py
msh/service/db/database/__init__.py
msh/service/output/__init__.py
msh/service/output/autoWrite.py
msh/service/output/pexpectInput.py
scripts/__init__.py
scripts/msh