Metadata-Version: 1.2
Name: msh
Version: 0.14
Summary: mac ssh client(linux can also use)
Home-page: https://github.com/mswang66/msh
Author: wls
Author-email: wanglongshengdf@gmail.com
License: GNU
Keywords: mac ssh
Platform: UNKNOWN
Requires-Python: ==2.7.*
